crime_hotspots_uk/__init__.py
crime_hotspots_uk/constants.py
crime_hotspots_uk/dataCollection.py
crime_hotspots_uk/locations/__init__.py
crime_hotspots_uk/locations/constituincies.geojson
crime_hotspots_uk/locations/constituincy.py
crime_hotspots_uk/locations/generic.py
crime_hotspots_uk/locations/police.py
crime_hotspots_uk-0.1.1.dist-info/AUTHORS.md
crime_hotspots_uk-0.1.1.dist-info/LICENSE.rst
crime_hotspots_uk-0.1.1.dist-info/METADATA
crime_hotspots_uk-0.1.1.dist-info/WHEEL
crime_hotspots_uk-0.1.1.dist-info/top_level.txt
crime_hotspots_uk-0.1.1.dist-info/RECORD
