Metadata-Version: 2.1
Name: crime-hotspots-uk
Version: 0.1.1
Summary: A python module that identifies and produces graphs of assult hotspots within the UK.
Home-page: https://github.com/Reclaim-The-Night-Leeds/crime-hotspots-uk
Author: Reclaim The Night Leeds
Author-email: RTNLeeds@gmail.com
License: MIT
Project-URL: Documentation, https://github.com/Reclaim-The-Night-Leeds/crime-hotspots-uk
Project-URL: Source, https://github.com/Reclaim-The-Night-Leeds/crime-hotspots-uk
Project-URL: Twitter, https://twitter.com/RTN_Leeds
Platform: any
Classifier: Development Status :: 4 - Beta
Classifier: Programming Language :: Python
Classifier: Framework :: Matplotlib
Classifier: Natural Language :: English
Classifier: License :: OSI Approved :: MIT License
Classifier: Intended Audience :: Science/Research
Classifier: Topic :: Scientific/Engineering :: Visualization
Classifier: Topic :: Sociology
Requires-Dist: sphinx-rtd-theme
Requires-Dist: recommonmark
Requires-Dist: sphinx (>=3.2.1)
Requires-Dist: numpy (>=1.19.2)
Requires-Dist: pandas (>=1.1.3)
Requires-Dist: pathlib
Requires-Dist: tqdm (>=4.51.0)
Requires-Dist: requests (~=2.23.0)
Requires-Dist: seaborn (>=0.11.1)
Requires-Dist: matplotlib (>=3.3.4)
Requires-Dist: scipy (>=1.5.4)
Requires-Dist: shapely (>=1.7.1)
Requires-Dist: datetime
Requires-Dist: geopandas
Requires-Dist: nbformat
Requires-Dist: nbconvert
Requires-Dist: ipykernel
Requires-Dist: ipywidgets
Requires-Dist: pyreadstat
Requires-Dist: pre-commit
Requires-Dist: importlib-metadata ; python_version < "3.8"
Provides-Extra: testing
Requires-Dist: setuptools ; extra == 'testing'
Requires-Dist: pytest ; extra == 'testing'
Requires-Dist: pytest-cov ; extra == 'testing'
Requires-Dist: nbformat ; extra == 'testing'
